Workbook

Sheet MENU
B2: RS MIRACLES - YOGYAKARTA
C4: ANALISIS KEPUTUSAN CAPEX - ALKES LABKLIN | I4: © Copyright Johny Setyawan & Niven A. Setyawan
F6: A. | G6: Alternatif Penawaran Capex
F7: B. | G7: Skema Revenue Sharing
F8: C. | G8: Answer
F10: Management Tools

Sheet ALTERNATIF PENAWARAN
A1: ALTERNATIF TAWARAN
B3: Sebagai Manajer Labklin yang baru, Bapak/Ibu dihadapkan pada kebutuhan untuk memperoleh Alat Analyzer Kimia yang sangat vital untuk memperlancar pelayanan. Pemasok alat Analyzer Kimia terpilih memberikan alternatif pendanaan dengan leasing (sewa guna usaha). Berikut adalah data penawaran dari pemasok:
B5: A. Tawaran dengan Leasing | C5: B. Tawaran dengan Pembelian | D5: C. Tawaran dgn Revenue Sharing per Pelayanan
B6: Pembayaran leasing sebesar Rp 280 juta per bulan selama 60 bulan (termasuk biaya pemeliharaan) | C6: Meminjam bank Senilai Rp 1,3 milyar dengan bunga 10% per tahun dengan declining balance | D6: Revenue sharing antara RS dengan Pemasok Alkes lewat persentase dari tarif, dimana Tarif Pelayanan ditentukan berdasarkan kesepakatan bersama
C7: Depresiasi metode garis lurus selama 5 tahun
C8: Nilai jual residu (taksiran trade-in) sebesar 10% dari harga beli | D8: Porsi untuk RS = 15% dari Tarif
C9: Biaya pemeliharaan sebesar Rp 20 juta per tahun | D9: Porsi untuk Pemasok = 85% dari Tarif
B10: Pendapatan, jasa medis, dan BHP dianggap sama untuk tawaran leasing maupun pembelian, oleh karenanya bisa diabaikan dalam perbandingan
B12: Berikan keputusan Bapak/Ibu dengan dukungan analisis keuangan!

Sheet SKEMA REVENUE SHARING
A1: SKEMA REVENUE SHARING
F2: A | G2: B | H2: C | I2: D | J2: 0.15
D3: 0.15 | E3: Proyeksi Vol Setahun | F3: =SUM(F56:F81) -> 1377000000 | G3: Proyeksi BO (Biaya Overhead) Langsung Setahun | H3: Proyeksi BO (Biaya Overhead) Alokasian Setahun | I3: Proyeksi Total Laba Bersih Operasi | J3: Proyeksi Total Laba Bersih Setelah Pajak (EAT) | K3: EAT Growth Rate | L3: PV Factor at 10% | M3: PV of Proceeds at 10%
A4: No. | B4: Nama Pemeriksaan | C4: Tarif | D4: Porsi RS | F4: Total Porsi RS | K4: 0.1
A5: 1 | B5: Albumin | C5: 150000 | D5: =$D$3*C5 -> 22500 | E5: 5658 | F5: =E5*D5 -> 127305000 | G5: =34*12*4000000 -> 1632000000 | H5: 240000000 | I5: =F3-G5-H5 -> -495000000 | J5: =(1-J2)*I5 -> -420750000 | K5: Tahun Ke - 1 | L5: =1*((1+0.1)^-A5) -> 0.90909091 | M5: =L5*J5 -> -382500000
A6: 2 | B6: Analisa Sperma | C6: 150000 | D6: =$D$3*C6 -> 22500 | E6: 6 | F6: =E6*D6 -> 135000 | G6: 34 orang personel Labklin (3 shift) dengan Gaji per bulan Rp 4 juta selama setahun | H6: Pembebanan biaya overhead (joint overhead costs) bersama dari unit-unit non pelayanan dengan dasar alokasi (daya serap) | I6: D = A - B - C | J6: =(1+$K$4)*J5 -> -4.62825e+08 | K6: Tahun Ke - 2 | L6: =1*((1+0.1)^-A6) -> 0.82644628 | M6: =L6*J6 -> -382500000
A7: 3 | B7: Anti HCV | C7: 150000 | D7: =$D$3*C7 -> 22500 | E7: 564 | F7: =E7*D7 -> 12690000 | J7: =(1+$K$4)*J6 -> -5.091075e+08 | K7: Tahun Ke - 3 | L7: =1*((1+0.1)^-A7) -> 0.7513148 | M7: =L7*J7 -> -382500000
A8: 4 | B8: Anti HIV | C8: 150000 | D8: =$D$3*C8 -> 22500 | E8: 4272 | F8: =E8*D8 -> 96120000 | J8: =(1+$K$4)*J7 -> -5.6001825e+08 | K8: Tahun Ke - 4 | L8: =1*((1+0.1)^-A8) -> 0.68301346 | M8: =L8*J8 -> -382500000
A9: 5 | B9: Analisa LCS | C9: 150000 | D9: =$D$3*C9 -> 22500 | E9: 6 | F9: =E9*D9 -> 135000 | J9: =(1+$K$4)*J8 -> -6.1602008e+08 | K9: Tahun Ke - 5 | L9: =1*((1+0.1)^-A9) -> 0.62092132 | M9: =L9*J9 -> -382500000
A10: 6 | B10: APTT / PTTK | C10: 150000 | D10: =$D$3*C10 -> 22500 | E10: 5160 | F10: =E10*D10 -> 116100000 | K10: TOTAL PV PROCEEDS | M10: =SUM(M5:M9) -> -1912500000
A11: 7 | B11: Bilirubin Direk | C11: 150000 | D11: =$D$3*C11 -> 22500 | E11: 1980 | F11: =E11*D11 -> 44550000
A12: 8 | B12: Bilirubin Total | C12: 150000 | D12: =$D$3*C12 -> 22500 | E12: 1980 | F12: =E12*D12 -> 44550000
A13: 9 | B13: Blood Gas Analisa (BGA) | C13: 150000 | D13: =$D$3*C13 -> 22500 | E13: 2166 | F13: =E13*D13 -> 48735000
A14: 10 | B14: Cholesterol Total | C14: 150000 | D14: =$D$3*C14 -> 22500 | E14: 11982 | F14: =E14*D14 -> 269595000
A15: 11 | B15: CK-MB | C15: 150000 | D15: =$D$3*C15 -> 22500 | E15: 510 | F15: =E15*D15 -> 11475000
A16: 12 | B16: Creatinin | C16: 150000 | D16: =$D$3*C16 -> 22500 | E16: 32208 | F16: =E16*D16 -> 724680000
A17: 13 | B17: CRP | C17: 150000 | D17: =$D$3*C17 -> 22500 | E17: 1698 | F17: =E17*D17 -> 38205000
A18: 14 | B18: Darah Lengkap | C18: 150000 | D18: =$D$3*C18 -> 22500 | E18: 5886 | F18: =E18*D18 -> 132435000
A19: 15 | B19: Darah Rutin | C19: 150000 | D19: =$D$3*C19 -> 22500 | E19: 68664 | F19: =E19*D19 -> 1544940000
A20: 16 | B20: D-Dimmer | C20: 150000 | D20: =$D$3*C20 -> 22500 | E20: 480 | F20: =E20*D20 -> 10800000
A21: 17 | B21: Dengue Blood | C21: 150000 | D21: =$D$3*C21 -> 22500 | E21: 2766 | F21: =E21*D21 -> 62235000
A22: 18 | B22: Faeces Rutin | C22: 150000 | D22: =$D$3*C22 -> 22500 | E22: 3582 | F22: =E22*D22 -> 80595000
... A81: 77 | B81: Imunohistokimia | C81: 150000 | D81: =$D$3*C81 -> 22500 | E81: 534 | F81: =E81*D81 -> 12015000

Sheet Ans
A1: JAWABAN
B3: Tawaran dengan Borrow & Purchase (dalam jutaan Rupiah)
B4: Tahun | C4: Principal Payment | D4: Interest Payment | E4: Maintenance Expense | F4: Total Expense | G4: PV Factor at 10% | H4: PV Expense | J4: KESIMPULAN:
B5: 1 | C5: 260 | D5: 130 | E5: 12 | F5: =SUM(B5:E5) -> 403 | G5: =1*((1+0.1)^-B5) -> 0.90909091 | H5: =G5*F5 -> 366.36364 | J5: Karena total PV Expense dari Leasing lebih kecil dari total PV Expense dari Pembelian; maka keputusan yang paling tepat adalah menggunakan tawaran LEASING.
B6: 2 | C6: 260 | D6: 104 | E6: 12 | F6: =SUM(B6:E6) -> 378 | G6: =1*((1+0.1)^-B6) -> 0.82644628 | H6: =G6*F6 -> 312.39669
B7: 3 | C7: 260 | D7: 78 | E7: 12 | F7: =SUM(B7:E7) -> 353 | G7: =1*((1+0.1)^-B7) -> 0.7513148 | H7: =G7*F7 -> 265.21412
B8: 4 | C8: 260 | D8: 52 | E8: 12 | F8: =SUM(B8:E8) -> 328 | G8: =1*((1+0.1)^-B8) -> 0.68301346 | H8: =G8*F8 -> 224.02841
B9: 5 | C9: 260 | D9: 26 | E9: 12 | F9: =SUM(B9:E9) -> 303 | G9: =1*((1+0.1)^-B9) -> 0.62092132 | H9: =G9*F9 -> 188.13916
B10: 5 | C10: Trade – in (130) | F10: -130 | G10: =1*((1+0.1)^-B10) -> 0.62092132 | H10: =G10*F10 -> -80.719772 | J10: Sedangkan kalau untuk KSO berarti pada akhir kontrak tidak ada transfer kepemilikan atas aset, sehingga sebenarnya Leasing adalah sama dengan KSO. Oleh karenanya KSO atau (Operating) Leasing lebih menguntungkan daripada Pembelian dengan didanai dengan Utang.
G11: Total | H11: =SUM(H5:H10) -> 1275.4223
B13: Tawaran dengan Leasing (dalam jutaan Rupiah)
B14: Tahun | C14: Lease Payment | G14: PV Factor at 10% | H14: PV Expense
B15: 1 | C15: 280 | G15: =1*((1+0.1)^-B15) -> 0.90909091 | H15: =C15*G15 -> 254.54545 | J15: Sedangkan untuk tawaran Revenue Sharing ternyata besarnya Biaya Overhead (Langsung dan Alokasian) telah menghabiskan akumulasi marjin tahunan sehingga hasil porsi 15% yang diperoleh RS tidak mencukupi, dan menyebabkan Negative EAT (Negative Earning After Tax) yang setelah di-nilai-tunai-kan (present value) justru menghasilkan PV Expense yang tertinggi dari ketiga tawaran yang ada.
B16: 2 | C16: 280 | G16: =1*((1+0.1)^-B16) -> 0.82644628 | H16: =C16*G16 -> 231.40496
B17: 3 | C17: 280 | G17: =1*((1+0.1)^-B17) -> 0.7513148 | H17: =C17*G17 -> 210.36814
B18: 4 | C18: 280 | G18: =1*((1+0.1)^-B18) -> 0.68301346 | H18: =C18*G18 -> 191.24377
B19: 5 | C19: 280 | G19: =1*((1+0.1)^-B19) -> 0.62092132 | H19: =C19*G19 -> 173.85797
G20: Total | H20: =SUM(H15:H19) -> 1061.4203
B22: Tawaran Revenue Sharing
B23: Tahun | C23: PROYEKSI NEGATIVE EAT | G23: PV Factor at 10% | H23: PV Expense | J23: Akurasi analisis keputusan investasi ini dapat ditingkatkan dengan menggunakan analisis berbasis produk yang lebih rinci.
B24: 1 | C24: =-('SKEMA REVENUE SHARING'!M5/1000000) -> 382.5 | G24: =1*((1+0.1)^-B24) -> 0.90909091 | H24: =C24*G24 -> 347.72727
B25: 2 | C25: =-('SKEMA REVENUE SHARING'!M6/1000000) -> 382.5 | G25: =1*((1+0.1)^-B25) -> 0.82644628 | H25: =C25*G25 -> 316.1157
B26: 3 | C26: =-('SKEMA REVENUE SHARING'!M7/1000000) -> 382.5 | G26: =1*((1+0.1)^-B26) -> 0.7513148 | H26: =C26*G26 -> 287.37791
B27: 4 | C27: =-('SKEMA REVENUE SHARING'!M8/1000000) -> 382.5 | G27: =1*((1+0.1)^-B27) -> 0.68301346 | H27: =C27*G27 -> 261.25265
B28: 5 | C28: =-('SKEMA REVENUE SHARING'!M9/1000000) -> 382.5 | G28: =1*((1+0.1)^-B28) -> 0.62092132 | H28: =C28*G28 -> 237.50241
G29: Total | H29: =SUM(H24:H28) -> 1449.9759
